bofhound/__init__.py
bofhound/__main__.py
bofhound/ad/__init__.py
bofhound/ad/adds.py
bofhound/ad/helpers/__init__.py
bofhound/ad/helpers/cert_utils.py
bofhound/ad/helpers/propertieslevel.py
bofhound/ad/helpers/trustdirection.py
bofhound/ad/helpers/trusttype.py
bofhound/ad/models/__init__.py
bofhound/ad/models/bloodhound_aiaca.py
bofhound/ad/models/bloodhound_certtemplate.py
bofhound/ad/models/bloodhound_computer.py
bofhound/ad/models/bloodhound_container.py
bofhound/ad/models/bloodhound_crossref.py
bofhound/ad/models/bloodhound_dnsnode.py
bofhound/ad/models/bloodhound_domain.py
bofhound/ad/models/bloodhound_domaintrust.py
bofhound/ad/models/bloodhound_enterpriseca.py
bofhound/ad/models/bloodhound_gpo.py
bofhound/ad/models/bloodhound_group.py
bofhound/ad/models/bloodhound_issuancepolicy.py
bofhound/ad/models/bloodhound_ntauthstore.py
bofhound/ad/models/bloodhound_object.py
bofhound/ad/models/bloodhound_ou.py
bofhound/ad/models/bloodhound_rootca.py
bofhound/ad/models/bloodhound_schema.py
bofhound/ad/models/bloodhound_user.py
bofhound/local/__init__.py
bofhound/local/localbroker.py
bofhound/local/models/__init__.py
bofhound/local/models/local_groupmembership.py
bofhound/local/models/local_privilegedsession.py
bofhound/local/models/local_registrysession.py
bofhound/local/models/local_session.py
bofhound/logger.py
bofhound/parsers/__init__.py
bofhound/parsers/brc4_ldap_sentinel.py
bofhound/parsers/data_sources.py
bofhound/parsers/ldap_search_bof.py
bofhound/parsers/netlocalgroup_bof.py
bofhound/parsers/netloggedon_bof.py
bofhound/parsers/netsession_bof.py
bofhound/parsers/parsertype.py
bofhound/parsers/parsing_pipeline.py
bofhound/parsers/regsession_bof.py
bofhound/parsers/types.py
bofhound/uploader.py
bofhound/writer.py
bofhound-0.4.23.dist-info/LICENSE
bofhound-0.4.23.dist-info/METADATA
bofhound-0.4.23.dist-info/WHEEL
bofhound-0.4.23.dist-info/entry_points.txt
bofhound-0.4.23.dist-info/RECORD
