Metadata-Version: 2.3
Name: bofhound
Version: 0.4.23
Summary: Parse output from common sources and transform it into BloodHound-ingestible data
Author: Adam Brown
Requires-Python: >=3.10,<4.0
Classifier: Programming Language :: Python :: 3
Classifier: Programming Language :: Python :: 3.10
Classifier: Programming Language :: Python :: 3.11
Classifier: Programming Language :: Python :: 3.12
Classifier: Programming Language :: Python :: 3.13
Requires-Dist: Flask (>=2.0,<3.0)
Requires-Dist: Jinja2 (>=3.0.3,<4.0.0)
Requires-Dist: MarkupSafe (>=2.0.1,<3.0.0)
Requires-Dist: Werkzeug (>=2.0.2,<3.0.0)
Requires-Dist: adidnsdump (>=1.4.0,<2.0.0)
Requires-Dist: asn1crypto (>=1.5.1,<2.0.0)
Requires-Dist: bloodhound (>=1.6,<2.0)
Requires-Dist: cffi (>=1.17.1,<2.0.0)
Requires-Dist: chardet (>=4.0,<5.0)
Requires-Dist: click (==8.1.8)
Requires-Dist: cryptography (>=36.0,<37.0)
Requires-Dist: dnspython (>=2.2,<3.0)
Requires-Dist: future (>=0.18.2,<0.19.0)
Requires-Dist: impacket (>=0.10.0,<0.11.0)
Requires-Dist: itsdangerous (>=2.0.1,<3.0.0)
Requires-Dist: ldap3 (>=2.9.1,<3.0.0)
Requires-Dist: ldapdomaindump (>=0.9.3,<0.10.0)
Requires-Dist: mythic (>=0.2.5,<0.3.0)
Requires-Dist: pyOpenSSL (>=22.0.0,<23.0.0)
Requires-Dist: pyasn1 (>=0.4.8,<0.5.0)
Requires-Dist: pycparser (>=2.21,<3.0)
Requires-Dist: pycryptodomex (>=3.14.0,<4.0.0)
Requires-Dist: requests (>=2.32.3,<3.0.0)
Requires-Dist: rich (>=12.5,<13.0)
Requires-Dist: six (>=1.16.0,<2.0.0)
Requires-Dist: syncer (>=2.0.3,<3.0.0)
Requires-Dist: typer (>=0.9,<0.10)
Project-URL: Homepage, https://github.com/coffeegist/bofhound
Project-URL: Repository, https://github.com/coffeegist/bofhound
